[
 {
  "word": "courtroom",
  "pos": [
   "noun"
  ],
  "cefr": "B1",
  "en": "a room in which a lawcourt sits",
  "syn": [
   "court"
  ]
 },
 {
  "word": "alibi",
  "pos": [
   "verb",
   "noun"
  ],
  "cefr": "B1",
  "en": "exonerate by means of an alibi",
  "syn": []
 },
 {
  "word": "wig",
  "pos": [
   "noun"
  ],
  "cefr": "B1",
  "en": "hairpiece covering the head and made of real or synthetic hair",
  "syn": []
 },
 {
  "word": "doorbell",
  "pos": [
   "noun"
  ],
  "cefr": "B1",
  "en": "a push button at an outer door that gives a ringing or buzzing signal when pushed",
  "syn": [
   "bell",
   "buzzer"
  ]
 },
 {
  "word": "footage",
  "pos": [
   "noun"
  ],
  "cefr": "B1",
  "en": "film that has been shot",
  "syn": []
 },
 {
  "word": "phony",
  "pos": [
   "adjective",
   "noun"
  ],
  "cefr": "B1",
  "en": "fraudulent",
  "syn": [
   "bogus",
   "fake",
   "phoney",
   "bastard"
  ]
 },
 {
  "word": "illusion",
  "pos": [
   "noun"
  ],
  "cefr": "B1",
  "en": "an erroneous mental representation",
  "syn": [
   "semblance"
  ]
 },
 {
  "word": "cocaine",
  "pos": [
   "noun"
  ],
  "cefr": "B1",
  "en": "a narcotic (alkaloid) extracted from coca leaves",
  "syn": [
   "cocain"
  ]
 },
 {
  "word": "autograph",
  "pos": [
   "verb",
   "noun"
  ],
  "cefr": "B1",
  "en": "mark with one's signature",
  "syn": [
   "inscribe"
  ]
 },
 {
  "word": "presume",
  "pos": [
   "verb"
  ],
  "cefr": "B2",
  "en": "take to be the case or to be true",
  "syn": [
   "assume",
   "take for granted"
  ]
 },
 {
  "word": "pony",
  "pos": [
   "noun"
  ],
  "cefr": "B2",
  "en": "a range horse of the western United States",
  "syn": []
 },
 {
  "word": "hose",
  "pos": [
   "verb",
   "noun"
  ],
  "cefr": "B2",
  "en": "water with a hose",
  "syn": [
   "hose down"
  ]
 },
 {
  "word": "mole",
  "pos": [
   "noun"
  ],
  "cefr": "B2",
  "en": "the molecular weight of a substance expressed in grams",
  "syn": [
   "gram molecule",
   "mol"
  ]
 },
 {
  "word": "surgical",
  "pos": [
   "adjective"
  ],
  "cefr": "B2",
  "en": "of or relating to or involving or used in surgery",
  "syn": []
 },
 {
  "word": "pod",
  "pos": [
   "verb",
   "noun"
  ],
  "cefr": "B2",
  "en": "take something out of its shell or pod",
  "syn": []
 },
 {
  "word": "tuck",
  "pos": [
   "verb",
   "noun"
  ],
  "cefr": "B2",
  "en": "fit snugly into",
  "syn": [
   "insert"
  ]
 },
 {
  "word": "chapel",
  "pos": [
   "noun"
  ],
  "cefr": "B2",
  "en": "a place of worship that has its own altar",
  "syn": []
 },
 {
  "word": "forgiveness",
  "pos": [
   "noun"
  ],
  "cefr": "B2",
  "en": "compassionate feelings that support a willingness to forgive",
  "syn": []
 },
 {
  "word": "martini",
  "pos": [
   "noun"
  ],
  "cefr": "B2",
  "en": "a cocktail made of gin (or vodka) with dry vermouth",
  "syn": []
 },
 {
  "word": "hustle",
  "pos": [
   "noun",
   "verb"
  ],
  "cefr": "B2",
  "en": "a swindle in which you cheat at gambling or persuade a person to buy worthless property",
  "syn": [
   "bunco",
   "bunco game",
   "bunko",
   "bunko game"
  ]
 },
 {
  "word": "ditch",
  "pos": [
   "noun",
   "verb"
  ],
  "cefr": "B2",
  "en": "a long narrow excavation in the earth",
  "syn": []
 },
 {
  "word": "lounge",
  "pos": [
   "verb",
   "noun"
  ],
  "cefr": "B2",
  "en": "sit or recline comfortably",
  "syn": []
 },
 {
  "word": "prosecution",
  "pos": [
   "noun"
  ],
  "cefr": "B2",
  "en": "the institution and conduct of legal proceedings against a defendant for criminal behavior",
  "syn": [
   "criminal prosecution"
  ]
 },
 {
  "word": "attic",
  "pos": [
   "adjective",
   "noun"
  ],
  "cefr": "B2",
  "en": "of or relating to Attica or its inhabitants or to the dialect spoken in Athens in classical times",
  "syn": []
 },
 {
  "word": "sis",
  "pos": [
   "noun"
  ],
  "cefr": "B2",
  "en": "a female person who has the same parents as another person",
  "syn": [
   "sister"
  ]
 },
 {
  "word": "saddle",
  "pos": [
   "verb",
   "noun"
  ],
  "cefr": "B2",
  "en": "put a saddle on",
  "syn": []
 },
 {
  "word": "cue",
  "pos": [
   "verb",
   "noun"
  ],
  "cefr": "B2",
  "en": "assist (somebody acting or reciting) by suggesting the next words of something forgotten or imperfectly learned",
  "syn": [
   "prompt",
   "remind"
  ]
 },
 {
  "word": "rot",
  "pos": [
   "verb",
   "noun"
  ],
  "cefr": "B2",
  "en": "break down",
  "syn": [
   "decompose",
   "molder",
   "moulder"
  ]
 },
 {
  "word": "blackmail",
  "pos": [
   "noun",
   "verb"
  ],
  "cefr": "B2",
  "en": "extortion of money by threats to divulge discrediting information",
  "syn": []
 },
 {
  "word": "shaft",
  "pos": [
   "verb",
   "noun"
  ],
  "cefr": "B2",
  "en": "equip with a shaft",
  "syn": []
 },
 {
  "word": "auto",
  "pos": [
   "noun"
  ],
  "cefr": "B2",
  "en": "a motor vehicle with four wheels",
  "syn": [
   "car",
   "automobile",
   "machine",
   "motorcar"
  ]
 },
 {
  "word": "insanity",
  "pos": [
   "noun"
  ],
  "cefr": "B2",
  "en": "relatively permanent disorder of the mind",
  "syn": []
 },
 {
  "word": "sub",
  "pos": [
   "verb",
   "noun"
  ],
  "cefr": "B2",
  "en": "be a substitute",
  "syn": [
   "substitute",
   "stand in",
   "fill in"
  ]
 },
 {
  "word": "pickup",
  "pos": [
   "noun"
  ],
  "cefr": "B2",
  "en": "a light truck with an open body and low sides and a tailboard",
  "syn": [
   "pickup truck"
  ]
 },
 {
  "word": "karate",
  "pos": [
   "noun"
  ],
  "cefr": "B2",
  "en": "a traditional Japanese system of unarmed combat",
  "syn": []
 },
 {
  "word": "violation",
  "pos": [
   "noun"
  ],
  "cefr": "B2",
  "en": "a crime less serious than a felony",
  "syn": [
   "misdemeanor",
   "misdemeanour",
   "infraction",
   "infringement"
  ]
 },
 {
  "word": "prep",
  "pos": [
   "noun"
  ],
  "cefr": "B2",
  "en": "preparatory school work done outside school (especially at home)",
  "syn": [
   "homework",
   "preparation"
  ]
 },
 {
  "word": "bass",
  "pos": [
   "adjective",
   "noun"
  ],
  "cefr": "B2",
  "en": "having or denoting a low vocal or instrumental range",
  "syn": [
   "deep"
  ]
 },
 {
  "word": "prostitute",
  "pos": [
   "noun",
   "verb"
  ],
  "cefr": "B2",
  "en": "a woman who engages in sexual intercourse for money",
  "syn": [
   "cocotte",
   "whore",
   "harlot",
   "bawd"
  ]
 },
 {
  "word": "hunch",
  "pos": [
   "verb",
   "noun"
  ],
  "cefr": "B2",
  "en": "round one's back by bending forward and drawing the shoulders forward",
  "syn": [
   "hump",
   "hunch forward",
   "hunch over"
  ]
 },
 {
  "word": "protocol",
  "pos": [
   "noun"
  ],
  "cefr": "B2",
  "en": "(computer science) rules determining the format and transmission of data",
  "syn": [
   "communications protocol"
  ]
 },
 {
  "word": "jolly",
  "pos": [
   "adverb",
   "verb",
   "adjective",
   "noun"
  ],
  "cefr": "B2",
  "en": "to certain extent or degree",
  "syn": [
   "reasonably",
   "moderately",
   "pretty",
   "somewhat"
  ]
 },
 {
  "word": "rum",
  "pos": [
   "adjective",
   "noun"
  ],
  "cefr": "B2",
  "en": "beyond or deviating from the usual or expected",
  "syn": [
   "curious",
   "funny",
   "odd",
   "peculiar"
  ]
 },
 {
  "word": "potion",
  "pos": [
   "noun"
  ],
  "cefr": "B2",
  "en": "a medicinal or magical or poisonous beverage",
  "syn": []
 },
 {
  "word": "brutal",
  "pos": [
   "adjective"
  ],
  "cefr": "B2",
  "en": "(of persons or their actions) able or disposed to inflict pain or suffering",
  "syn": [
   "barbarous",
   "cruel",
   "fell",
   "roughshod"
  ]
 },
 {
  "word": "fist",
  "pos": [
   "noun"
  ],
  "cefr": "B2",
  "en": "a hand with the fingers clenched in the palm (as for hitting)",
  "syn": [
   "clenched fist"
  ]
 },
 {
  "word": "spinning",
  "pos": [
   "noun"
  ],
  "cefr": "B2",
  "en": "creating thread",
  "syn": []
 },
 {
  "word": "precinct",
  "pos": [
   "noun"
  ],
  "cefr": "B2",
  "en": "a district of a city or town marked out for administrative purposes",
  "syn": []
 },
 {
  "word": "lobster",
  "pos": [
   "noun"
  ],
  "cefr": "B2",
  "en": "flesh of a lobster",
  "syn": []
 },
 {
  "word": "armor",
  "pos": [
   "verb",
   "noun"
  ],
  "cefr": "B2",
  "en": "equip with armor",
  "syn": [
   "armour"
  ]
 },
 {
  "word": "distress",
  "pos": [
   "verb",
   "noun"
  ],
  "cefr": "B2",
  "en": "bring into difficulties or distress, especially financial hardship",
  "syn": [
   "straiten"
  ]
 },
 {
  "word": "salute",
  "pos": [
   "noun",
   "verb"
  ],
  "cefr": "B2",
  "en": "an act of honor or courteous recognition",
  "syn": [
   "salutation"
  ]
 },
 {
  "word": "liable",
  "pos": [
   "adjective"
  ],
  "cefr": "B2",
  "en": "at risk of or subject to experiencing something usually unpleasant",
  "syn": [
   "apt(p)",
   "liable(p)"
  ]
 },
 {
  "word": "abortion",
  "pos": [
   "noun"
  ],
  "cefr": "B2",
  "en": "termination of pregnancy",
  "syn": []
 },
 {
  "word": "platoon",
  "pos": [
   "noun"
  ],
  "cefr": "B2",
  "en": "a military unit that is a subdivision of a company",
  "syn": []
 },
 {
  "word": "notify",
  "pos": [
   "verb"
  ],
  "cefr": "B2",
  "en": "inform (somebody) of something",
  "syn": [
   "advise",
   "give notice",
   "send word",
   "apprise"
  ]
 },
 {
  "word": "integrity",
  "pos": [
   "noun"
  ],
  "cefr": "B2",
  "en": "an undivided or unbroken completeness or totality with nothing wanting",
  "syn": [
   "unity",
   "wholeness"
  ]
 },
 {
  "word": "bounty",
  "pos": [
   "noun"
  ],
  "cefr": "B2",
  "en": "payment or reward (especially from a government) for acts such as catching criminals or killing predatory animals or enlisting in the military",
  "syn": [
   "premium"
  ]
 },
 {
  "word": "prosecutor",
  "pos": [
   "noun"
  ],
  "cefr": "B2",
  "en": "a government official who conducts criminal prosecutions on behalf of the state",
  "syn": [
   "public prosecutor",
   "prosecuting officer",
   "prosecuting attorney"
  ]
 },
 {
  "word": "gracious",
  "pos": [
   "adjective"
  ],
  "cefr": "B2",
  "en": "characterized by charm, good taste, and generosity of spirit",
  "syn": []
 },
 {
  "word": "savage",
  "pos": [
   "verb",
   "noun",
   "adjective"
  ],
  "cefr": "B2",
  "en": "attack brutally and fiercely",
  "syn": []
 },
 {
  "word": "harsh",
  "pos": [
   "adjective"
  ],
  "cefr": "B2",
  "en": "unpleasantly stern",
  "syn": [
   "rough"
  ]
 },
 {
  "word": "haul",
  "pos": [
   "verb",
   "noun"
  ],
  "cefr": "B2",
  "en": "draw slowly or heavily",
  "syn": [
   "hale",
   "cart",
   "drag"
  ]
 },
 {
  "word": "bam",
  "pos": [
   "noun"
  ],
  "cefr": "B2",
  "en": "an ancient city in southeastern Iran",
  "syn": []
 },
 {
  "word": "gag",
  "pos": [
   "noun",
   "verb"
  ],
  "cefr": "B2",
  "en": "a humorous anecdote or remark intended to provoke laughter",
  "syn": [
   "joke",
   "laugh",
   "jest",
   "jape"
  ]
 },
 {
  "word": "sting",
  "pos": [
   "verb",
   "noun"
  ],
  "cefr": "B2",
  "en": "cause a sharp or stinging pain or discomfort",
  "syn": [
   "bite",
   "burn"
  ]
 },
 {
  "word": "cord",
  "pos": [
   "verb",
   "noun"
  ],
  "cefr": "B2",
  "en": "stack in cords",
  "syn": []
 },
 {
  "word": "guardian",
  "pos": [
   "noun"
  ],
  "cefr": "B2",
  "en": "a person who cares for persons or property",
  "syn": [
   "defender",
   "protector",
   "shielder"
  ]
 },
 {
  "word": "lonesome",
  "pos": [
   "adjective"
  ],
  "cefr": "B2",
  "en": "being the only one",
  "syn": [
   "lone(a)",
   "lonesome(a)",
   "only(a)",
   "sole(a)"
  ]
 },
 {
  "word": "nun",
  "pos": [
   "noun"
  ],
  "cefr": "B2",
  "en": "a woman religious",
  "syn": []
 },
 {
  "word": "grease",
  "pos": [
   "verb",
   "noun"
  ],
  "cefr": "B2",
  "en": "lubricate with grease",
  "syn": []
 },
 {
  "word": "stud",
  "pos": [
   "verb",
   "noun"
  ],
  "cefr": "B2",
  "en": "scatter or intersperse like dots or studs",
  "syn": [
   "dot",
   "constellate"
  ]
 },
 {
  "word": "geek",
  "pos": [
   "noun"
  ],
  "cefr": "B2",
  "en": "a carnival performer who does disgusting acts",
  "syn": []
 },
 {
  "word": "pervert",
  "pos": [
   "noun",
   "verb"
  ],
  "cefr": "B2",
  "en": "a person whose behavior deviates from what is acceptable especially in sexual behavior",
  "syn": [
   "deviant",
   "deviate",
   "degenerate"
  ]
 },
 {
  "word": "gravity",
  "pos": [
   "noun"
  ],
  "cefr": "B2",
  "en": "(physics) the force of attraction between all masses in the universe",
  "syn": [
   "gravitation",
   "gravitational attraction",
   "gravitational force"
  ]
 },
 {
  "word": "pledge",
  "pos": [
   "noun",
   "verb"
  ],
  "cefr": "B2",
  "en": "a deposit of personal property as security for a debt",
  "syn": []
 },
 {
  "word": "slick",
  "pos": [
   "verb",
   "noun",
   "adjective"
  ],
  "cefr": "B2",
  "en": "make slick or smooth",
  "syn": [
   "sleek"
  ]
 },
 {
  "word": "eighth",
  "pos": [
   "adjective",
   "noun"
  ],
  "cefr": "B2",
  "en": "coming next after the seventh and just before the ninth in position",
  "syn": [
   "8th"
  ]
 },
 {
  "word": "dispatch",
  "pos": [
   "noun",
   "verb"
  ],
  "cefr": "B2",
  "en": "an official report (usually sent in haste)",
  "syn": [
   "despatch",
   "communique"
  ]
 },
 {
  "word": "clearance",
  "pos": [
   "noun"
  ],
  "cefr": "B2",
  "en": "the distance by which one thing clears another",
  "syn": []
 },
 {
  "word": "chow",
  "pos": [
   "noun"
  ],
  "cefr": "B2",
  "en": "the imperial dynasty of China from 1122 to 221 BC",
  "syn": [
   "Zhou",
   "Zhou dynasty",
   "Chou",
   "Chou dynasty"
  ]
 },
 {
  "word": "clamp",
  "pos": [
   "verb",
   "noun"
  ],
  "cefr": "B2",
  "en": "fasten or fix with a clamp",
  "syn": []
 },
 {
  "word": "shovel",
  "pos": [
   "verb",
   "noun"
  ],
  "cefr": "B2",
  "en": "dig with or as if with a shovel",
  "syn": []
 },
 {
  "word": "plea",
  "pos": [
   "noun"
  ],
  "cefr": "B2",
  "en": "a humble request for help from someone in authority",
  "syn": [
   "supplication"
  ]
 },
 {
  "word": "jackass",
  "pos": [
   "noun"
  ],
  "cefr": "B2",
  "en": "a man who is a stupid incompetent fool",
  "syn": [
   "fathead",
   "goof",
   "goofball",
   "bozo"
  ]
 },
 {
  "word": "loop",
  "pos": [
   "verb",
   "noun"
  ],
  "cefr": "B2",
  "en": "move in loops",
  "syn": []
 },
 {
  "word": "classified",
  "pos": [
   "adjective",
   "noun"
  ],
  "cefr": "B2",
  "en": "arranged into classes",
  "syn": []
 },
 {
  "word": "driveway",
  "pos": [
   "noun"
  ],
  "cefr": "B2",
  "en": "a road leading up to a private house",
  "syn": [
   "drive",
   "private road"
  ]
 },
 {
  "word": "confidential",
  "pos": [
   "adjective"
  ],
  "cefr": "B2",
  "en": "entrusted with private information and the confidence of another",
  "syn": []
 },
 {
  "word": "rabbi",
  "pos": [
   "noun"
  ],
  "cefr": "B2",
  "en": "spiritual leader of a Jewish congregation",
  "syn": []
 },
 {
  "word": "enforcement",
  "pos": [
   "noun"
  ],
  "cefr": "B2",
  "en": "the act of enforcing",
  "syn": []
 },
 {
  "word": "galaxy",
  "pos": [
   "noun"
  ],
  "cefr": "B2",
  "en": "a splendid assemblage (especially of famous people)",
  "syn": []
 },
 {
  "word": "inappropriate",
  "pos": [
   "adjective"
  ],
  "cefr": "B2",
  "en": "not suitable for a particular occasion etc",
  "syn": []
 },
 {
  "word": "mattress",
  "pos": [
   "noun"
  ],
  "cefr": "B2",
  "en": "a large thick pad filled with resilient material and often incorporating coiled springs, used as a bed or part of a bed",
  "syn": []
 },
 {
  "word": "memo",
  "pos": [
   "noun"
  ],
  "cefr": "B2",
  "en": "a written proposal or reminder",
  "syn": [
   "memorandum",
   "memoranda"
  ]
 },
 {
  "word": "innocence",
  "pos": [
   "noun"
  ],
  "cefr": "B2",
  "en": "the quality of innocent naivete",
  "syn": [
   "artlessness",
   "ingenuousness",
   "naturalness"
  ]
 },
 {
  "word": "ninth",
  "pos": [
   "adjective",
   "noun"
  ],
  "cefr": "B2",
  "en": "coming next after the eighth and just before the tenth in position",
  "syn": [
   "9th"
  ]
 },
 {
  "word": "siren",
  "pos": [
   "noun"
  ],
  "cefr": "B2",
  "en": "a sea nymph (part woman and part bird) supposed to lure sailors to destruction on the rocks where the nymphs lived",
  "syn": []
 },
 {
  "word": "pregnancy",
  "pos": [
   "noun"
  ],
  "cefr": "B2",
  "en": "the state of being pregnant",
  "syn": [
   "gestation",
   "maternity"
  ]
 },
 {
  "word": "starboard",
  "pos": [
   "adjective",
   "verb",
   "noun"
  ],
  "cefr": "B2",
  "en": "located on the right side of a ship or aircraft",
  "syn": []
 },
 {
  "word": "gasoline",
  "pos": [
   "noun"
  ],
  "cefr": "B2",
  "en": "a volatile flammable mixture of hydrocarbons (hexane and heptane and octane etc.) derived from petroleum",
  "syn": [
   "gasolene",
   "gas",
   "petrol"
  ]
 },
 {
  "word": "detention",
  "pos": [
   "noun"
  ],
  "cefr": "B2",
  "en": "a state of being confined (usually for a short time)",
  "syn": [
   "detainment",
   "hold",
   "custody"
  ]
 },
 {
  "word": "urine",
  "pos": [
   "noun"
  ],
  "cefr": "B2",
  "en": "liquid excretory product",
  "syn": [
   "piss",
   "pee",
   "piddle",
   "weewee"
  ]
 },
 {
  "word": "beep",
  "pos": [
   "noun",
   "verb"
  ],
  "cefr": "B2",
  "en": "a short high tone produced as a signal or warning",
  "syn": [
   "bleep"
  ]
 },
 {
  "word": "riot",
  "pos": [
   "verb",
   "noun"
  ],
  "cefr": "B2",
  "en": "take part in a riot",
  "syn": []
 },
 {
  "word": "kidnap",
  "pos": [
   "verb"
  ],
  "cefr": "B2",
  "en": "take away to an undisclosed location against their will and usually in order to extract a ransom",
  "syn": [
   "nobble",
   "abduct",
   "snatch"
  ]
 },
 {
  "word": "morphine",
  "pos": [
   "noun"
  ],
  "cefr": "B2",
  "en": "an alkaloid narcotic drug extracted from opium",
  "syn": [
   "morphia"
  ]
 },
 {
  "word": "cheerleader",
  "pos": [
   "noun"
  ],
  "cefr": "B2",
  "en": "an enthusiastic and vocal supporter",
  "syn": []
 },
 {
  "word": "fart",
  "pos": [
   "verb",
   "noun"
  ],
  "cefr": "B2",
  "en": "expel intestinal gases through the anus",
  "syn": [
   "break wind"
  ]
 },
 {
  "word": "whereabouts",
  "pos": [
   "noun"
  ],
  "cefr": "B2",
  "en": "the general location where something is",
  "syn": []
 },
 {
  "word": "creeps",
  "pos": [
   "noun"
  ],
  "cefr": "B2",
  "en": "a disease of cattle and sheep attributed to a dietary deficiency",
  "syn": []
 },
 {
  "word": "drift",
  "pos": [
   "noun",
   "verb"
  ],
  "cefr": "B2",
  "en": "a force that moves something along",
  "syn": [
   "impetus",
   "impulsion"
  ]
 },
 {
  "word": "psychotic",
  "pos": [
   "noun",
   "adjective"
  ],
  "cefr": "B2",
  "en": "a person afflicted with psychosis",
  "syn": [
   "psychotic person",
   "psycho"
  ]
 },
 {
  "word": "tech",
  "pos": [
   "noun"
  ],
  "cefr": "B2",
  "en": "a school teaching mechanical and industrial arts and the applied sciences",
  "syn": [
   "technical school"
  ]
 },
 {
  "word": "torpedo",
  "pos": [
   "verb",
   "noun"
  ],
  "cefr": "B2",
  "en": "attack or hit with torpedoes",
  "syn": []
 },
 {
  "word": "hereby",
  "pos": [
   "adverb"
  ],
  "cefr": "B2",
  "en": "(formal) by means of this",
  "syn": [
   "herewith"
  ]
 },
 {
  "word": "intact",
  "pos": [
   "adjective"
  ],
  "cefr": "B2",
  "en": "constituting the undiminished entirety",
  "syn": [
   "integral",
   "entire"
  ]
 },
 {
  "word": "chap",
  "pos": [
   "verb",
   "noun"
  ],
  "cefr": "B2",
  "en": "crack due to dehydration",
  "syn": []
 },
 {
  "word": "shipment",
  "pos": [
   "noun"
  ],
  "cefr": "B2",
  "en": "goods carried by a large vehicle",
  "syn": [
   "cargo",
   "lading",
   "freight",
   "load"
  ]
 },
 {
  "word": "deceased",
  "pos": [
   "adjective",
   "noun"
  ],
  "cefr": "B2",
  "en": "dead",
  "syn": [
   "asleep(p)",
   "at peace(p)",
   "at rest(p)",
   "departed"
  ]
 },
 {
  "word": "prophecy",
  "pos": [
   "noun"
  ],
  "cefr": "B2",
  "en": "knowledge of the future (usually said to be obtained from a divine source)",
  "syn": [
   "prognostication",
   "vaticination"
  ]
 },
 {
  "word": "bunk",
  "pos": [
   "verb",
   "noun"
  ],
  "cefr": "B2",
  "en": "avoid paying",
  "syn": [
   "beat"
  ]
 },
 {
  "word": "velvet",
  "pos": [
   "noun",
   "adjective"
  ],
  "cefr": "B2",
  "en": "a silky densely piled fabric with a plain back",
  "syn": []
 },
 {
  "word": "puke",
  "pos": [
   "verb",
   "noun"
  ],
  "cefr": "B2",
  "en": "eject the contents of the stomach through the mouth",
  "syn": [
   "vomit",
   "vomit up",
   "purge",
   "cast"
  ]
 },
 {
  "word": "timer",
  "pos": [
   "noun"
  ],
  "cefr": "B2",
  "en": "a timepiece that measures a time interval and signals its end",
  "syn": []
 },
 {
  "word": "scrub",
  "pos": [
   "adjective",
   "noun",
   "verb"
  ],
  "cefr": "B2",
  "en": "(of domestic animals) not selectively bred",
  "syn": []
 },
 {
  "word": "sperm",
  "pos": [
   "noun"
  ],
  "cefr": "B2",
  "en": "the male reproductive cell",
  "syn": [
   "sperm cell",
   "spermatozoon",
   "spermatozoan"
  ]
 },
 {
  "word": "brat",
  "pos": [
   "noun"
  ],
  "cefr": "B2",
  "en": "a very troublesome child",
  "syn": [
   "terror",
   "little terror",
   "holy terror"
  ]
 },
 {
  "word": "erase",
  "pos": [
   "verb"
  ],
  "cefr": "B2",
  "en": "remove from memory or existence",
  "syn": [
   "wipe out"
  ]
 },
 {
  "word": "breach",
  "pos": [
   "verb",
   "noun"
  ],
  "cefr": "B2",
  "en": "act in disregard of laws, rules, contracts, or promises",
  "syn": [
   "transgress",
   "offend",
   "infract",
   "violate"
  ]
 },
 {
  "word": "bluff",
  "pos": [
   "adjective",
   "verb",
   "noun"
  ],
  "cefr": "B2",
  "en": "very steep",
  "syn": [
   "bold",
   "sheer"
  ]
 },
 {
  "word": "cavalry",
  "pos": [
   "noun"
  ],
  "cefr": "B2",
  "en": "troops trained to fight on horseback",
  "syn": [
   "horse cavalry",
   "horse"
  ]
 },
 {
  "word": "ashore",
  "pos": [
   "adverb"
  ],
  "cefr": "B2",
  "en": "towards the shore from the water",
  "syn": []
 },
 {
  "word": "bedtime",
  "pos": [
   "noun"
  ],
  "cefr": "B2",
  "en": "the time you go to bed",
  "syn": []
 },
 {
  "word": "crib",
  "pos": [
   "verb",
   "noun"
  ],
  "cefr": "B2",
  "en": "use a crib, as in an exam",
  "syn": []
 },
 {
  "word": "drunken",
  "pos": [
   "adjective"
  ],
  "cefr": "B2",
  "en": "given to or marked by the consumption of alcohol",
  "syn": [
   "bibulous",
   "boozy",
   "sottish"
  ]
 },
 {
  "word": "civilized",
  "pos": [
   "adjective"
  ],
  "cefr": "B2",
  "en": "having a high state of culture and development both social and technological",
  "syn": [
   "civilised"
  ]
 },
 {
  "word": "scam",
  "pos": [
   "verb",
   "noun"
  ],
  "cefr": "B2",
  "en": "deprive of by deceit",
  "syn": [
   "victimize",
   "swindle",
   "rook",
   "goldbrick"
  ]
 },
 {
  "word": "booty",
  "pos": [
   "noun"
  ],
  "cefr": "B2",
  "en": "goods or money obtained illegally",
  "syn": [
   "loot",
   "pillage",
   "plunder",
   "prize"
  ]
 },
 {
  "word": "pinch",
  "pos": [
   "verb",
   "noun"
  ],
  "cefr": "B2",
  "en": "squeeze tightly between the fingers",
  "syn": [
   "squeeze",
   "twinge",
   "tweet",
   "nip"
  ]
 },
 {
  "word": "rendezvous",
  "pos": [
   "verb",
   "noun"
  ],
  "cefr": "B2",
  "en": "meet at a rendezvous",
  "syn": []
 },
 {
  "word": "den",
  "pos": [
   "noun"
  ],
  "cefr": "B2",
  "en": "the habitation of wild animals",
  "syn": [
   "lair"
  ]
 },
 {
  "word": "yen",
  "pos": [
   "verb",
   "noun"
  ],
  "cefr": "B2",
  "en": "have a desire for something or someone who is not present",
  "syn": [
   "ache",
   "yearn",
   "pine",
   "languish"
  ]
 },
 {
  "word": "bathtub",
  "pos": [
   "noun"
  ],
  "cefr": "B2",
  "en": "a relatively large open container that you fill with water and use to wash the body",
  "syn": [
   "bathing tub",
   "tub"
  ]
 },
 {
  "word": "chorus",
  "pos": [
   "verb",
   "noun"
  ],
  "cefr": "B2",
  "en": "utter in unison",
  "syn": []
 },
 {
  "word": "ketchup",
  "pos": [
   "noun"
  ],
  "cefr": "B2",
  "en": "thick spicy sauce made from tomatoes",
  "syn": [
   "catsup",
   "cetchup",
   "tomato ketchup"
  ]
 },
 {
  "word": "stereo",
  "pos": [
   "adjective",
   "noun"
  ],
  "cefr": "B2",
  "en": "designating the reproduction of sound using two or more independent audio channels",
  "syn": [
   "stereophonic",
   "two-channel"
  ]
 },
 {
  "word": "compartment",
  "pos": [
   "noun"
  ],
  "cefr": "B2",
  "en": "a space into which an area is subdivided",
  "syn": []
 },
 {
  "word": "parlor",
  "pos": [
   "noun"
  ],
  "cefr": "B2",
  "en": "reception room in an inn or club where visitors can be received",
  "syn": [
   "parlour"
  ]
 },
 {
  "word": "flashlight",
  "pos": [
   "noun"
  ],
  "cefr": "B2",
  "en": "a small portable battery-powered electric lamp",
  "syn": [
   "torch"
  ]
 }
]